{
  "version": "7",
  "dialect": "postgresql",
  "entries": [
    {
      "idx": 0,
      "version": "7",
      "when": 1781528323959,
      "tag": "0000_shallow_zarek",
      "breakpoints": true
    },
    {
      "idx": 1,
      "version": "7",
      "when": 1781533580065,
      "tag": "0001_lowly_network",
      "breakpoints": true
    },
    {
      "idx": 2,
      "version": "7",
      "when": 1781935565450,
      "tag": "0002_powerful_winter_soldier",
      "breakpoints": true
    },
    {
      "idx": 3,
      "version": "7",
      "when": 1781964850495,
      "tag": "0003_wise_randall",
      "breakpoints": true
    }
  ]
}